README.txt
setup.py
ais_package/__init__.py
ais_package.egg-info/PKG-INFO
ais_package.egg-info/SOURCES.txt
ais_package.egg-info/dependency_links.txt
ais_package.egg-info/top_level.txt