Metadata-Version: 1.1
Name: ais-package
Version: 0.0.1
Summary: Test package!
Home-page: UNKNOWN
Author: Ed Valdez
Author-email: efvaldez.consultant@adb.org
License: MIT
Keywords: AIS
Platform: UNKNOWN
Classifier: Development Status :: 5 - Production/Stable
Classifier: Intended Audience :: Education
Classifier: Operating System :: Microsoft :: Windows :: Windows 10
Classifier: License :: OSI Approved :: MIT License
Classifier: Programming Language :: Python :: 3
